{"trial_id": "01", "hyperparameters": {"space": [{"class_name": "Int", "config": {"name": "units_input", "default": null, "conditions": [], "min_value": 32, "max_value": 512, "step": 32, "sampling": "linear"}}, {"class_name": "Int", "config": {"name": "num_layers", "default": null, "conditions": [], "min_value": 1, "max_value": 5, "step": 1, "sampling": "linear"}}, {"class_name": "Int", "config": {"name": "units_0", "default": null, "conditions": [], "min_value": 32, "max_value": 512, "step": 32, "sampling": "linear"}}, {"class_name": "Float", "config": {"name": "learning_rate", "default": 1e-05, "conditions": [], "min_value": 1e-05, "max_value": 0.01, "step": null, "sampling": "log"}}, {"class_name": "Int", "config": {"name": "units_1", "default": null, "conditions": [], "min_value": 32, "max_value": 512, "step": 32, "sampling": "linear"}}, {"class_name": "Int", "config": {"name": "units_2", "default": null, "conditions": [], "min_value": 32, "max_value": 512, "step": 32, "sampling": "linear"}}, {"class_name": "Int", "config": {"name": "units_3", "default": null, "conditions": [], "min_value": 32, "max_value": 512, "step": 32, "sampling": "linear"}}, {"class_name": "Int", "config": {"name": "units_4", "default": null, "conditions": [], "min_value": 32, "max_value": 512, "step": 32, "sampling": "linear"}}], "values": {"units_input": 480, "num_layers": 3, "units_0": 384, "learning_rate": 0.0025284024026362524, "units_1": 448, "units_2": 224, "units_3": 320, "units_4": 256}}, "metrics": {"metrics": {"accuracy": {"direction": "max", "observations": [{"value": [0.9638718366622925], "step": 5}]}, "loss": {"direction": "min", "observations": [{"value": [0.11489791423082352], "step": 5}]}, "prc": {"direction": "min", "observations": [{"value": [0.9813416004180908], "step": 5}]}, "precision": {"direction": "max", "observations": [{"value": [0.9541884064674377], "step": 5}]}, "recall": {"direction": "max", "observations": [{"value": [0.9808303117752075], "step": 5}]}, "val_accuracy": {"direction": "max", "observations": [{"value": [0.9658071398735046], "step": 5}]}, "val_loss": {"direction": "min", "observations": [{"value": [0.10200829058885574], "step": 5}]}, "val_prc": {"direction": "max", "observations": [{"value": [0.9901173710823059], "step": 5}]}, "val_precision": {"direction": "max", "observations": [{"value": [0.9529914259910583], "step": 5}]}, "val_recall": {"direction": "max", "observations": [{"value": [0.9852724671363831], "step": 5}]}}}, "score": 0.9901173710823059, "best_step": 5, "status": "COMPLETED", "message": null}